sunra_client/__init__.py
sunra_client/auth.py
sunra_client/client.py
sunra_client/py.typed
sunra_client-0.5.0.dist-info/METADATA
sunra_client-0.5.0.dist-info/WHEEL
sunra_client-0.5.0.dist-info/top_level.txt
sunra_client-0.5.0.dist-info/RECORD
