Metadata-Version: 2.4
Name: sunra_client
Version: 0.5.0
Summary: Python client for sunra.ai
Author: Features & Labels <support@sunra.ai>
Project-URL: homepage, https://sunra.ai
Project-URL: repository, https://github.com/sunra-ai/sunra-clients
Requires-Python: >=3.8
Requires-Dist: httpx<1,>=0.21.0
Requires-Dist: httpx-sse<0.5,>=0.4.0
Requires-Dist: requests
Provides-Extra: docs
Requires-Dist: sphinx; extra == "docs"
Requires-Dist: sphinx-rtd-theme; extra == "docs"
Requires-Dist: sphinx-autodoc-typehints; extra == "docs"
Provides-Extra: test
Requires-Dist: pytest; extra == "test"
Requires-Dist: pytest-asyncio; extra == "test"
Requires-Dist: pillow; extra == "test"
Provides-Extra: dev
Requires-Dist: sunra_client[docs,test]; extra == "dev"
